mcapi-0.3.dist-info/RECORD
mcapi-0.3.dist-info/DESCRIPTION.rst
mcapi-0.3.dist-info/WHEEL
mcapi-0.3.dist-info/metadata.json
mcapi-0.3.dist-info/METADATA
mcapi-0.3.dist-info/top_level.txt
mcapi/exceptions.py
mcapi/__init__.py
mcapi/profile.py
